LICENSE
README.md
setup.py
pyutils/__init__.py
pyutils/activation.py
pyutils/compute.py
pyutils/config.py
pyutils/distribution_sampler.py
pyutils/general.py
pyutils/initializer.py
pyutils/metric.py
pyutils/normalization.py
pyutils/plot.py
pyutils/quantize.py
pyutils/torch_train.py
pyutils/typing.py
pyutils/version.py
pyutils/datasets/__init__.py
pyutils/datasets/builder.py
pyutils/datasets/cars.py
pyutils/datasets/cifar10.py
pyutils/datasets/cifar100.py
pyutils/datasets/dogs.py
pyutils/datasets/fashionmnist.py
pyutils/datasets/flowers.py
pyutils/datasets/mnist.py
pyutils/datasets/svhn.py
pyutils/datasets/tinyimagenet.py
pyutils/datasets/vowel.py
pyutils/loss/__init__.py
pyutils/loss/alpha_divergence.py
pyutils/loss/ce_smooth.py
pyutils/loss/dkd.py
pyutils/loss/dual_focal.py
pyutils/loss/focal_smooth.py
pyutils/loss/kd.py
pyutils/loss/utils.py
pyutils/lr_scheduler/__init__.py
pyutils/lr_scheduler/warmup_cosine_restart.py
pyutils/optimizer/__init__.py
pyutils/optimizer/adam_gc.py
pyutils/optimizer/dadapt_adam.py
pyutils/optimizer/dadapt_sgd.py
pyutils/optimizer/gld.py
pyutils/optimizer/lookahead.py
pyutils/optimizer/prodigy.py
pyutils/optimizer/radam.py
pyutils/optimizer/sam.py
pyutils/optimizer/sgd_gc.py
pyutils/optimizer/smtp.py
pyutils/quant/__init__.py
pyutils/quant/lsq.py
torchonn_pyutils.egg-info/PKG-INFO
torchonn_pyutils.egg-info/SOURCES.txt
torchonn_pyutils.egg-info/dependency_links.txt
torchonn_pyutils.egg-info/requires.txt
torchonn_pyutils.egg-info/top_level.txt