Metadata-Version: 2.1
Name: torchonn-pyutils
Version: 0.0.3.2
Summary: Python/Pytorch Utility
Home-page: https://github.com/JeremieMelo/pyutility
Author: Jiaqi Gu
Author-email: jqgu@utexas.edu
License: MIT
Requires-Python: >=3
License-File: LICENSE
Requires-Dist: numpy>=1.19.2
Requires-Dist: torchvision>=0.9.0.dev20210130
Requires-Dist: tqdm>=4.56.0
Requires-Dist: setuptools>=61.0.0
Requires-Dist: torch>=1.8.0
Requires-Dist: matplotlib>=3.3.4
Requires-Dist: svglib>=1.1.0
Requires-Dist: scipy>=1.5.4
Requires-Dist: scikit-learn>=0.24.1
Requires-Dist: pyyaml>=5.1.1
Requires-Dist: tensorflow>=2.5.0
